pymmaster/__init__.py
pymmaster/mmaster_tools.py
pymmaster-0.1.2.data/scripts/CleanMicMac.sh
pymmaster-0.1.2.data/scripts/Link_MMASTER_Files.sh
pymmaster-0.1.2.data/scripts/PostProcessMicMac.sh
pymmaster-0.1.2.data/scripts/RunMicMacAster_batch.sh
pymmaster-0.1.2.data/scripts/WorkFlowASTER.sh
pymmaster-0.1.2.data/scripts/WorkFlow_WaterMask.sh
pymmaster-0.1.2.data/scripts/apply_mmaster_corrections.py
pymmaster-0.1.2.data/scripts/batch_coregister_tiles.py
pymmaster-0.1.2.data/scripts/bias_correct_tiles.py
pymmaster-0.1.2.data/scripts/create_micmac_xml.py
pymmaster-0.1.2.data/scripts/mmaster_bias_correction.py
pymmaster-0.1.2.data/scripts/mosaic_micmac_tiles.py
pymmaster-0.1.2.data/scripts/process_l1a.sh
pymmaster-0.1.2.data/scripts/process_mmaster.sh
pymmaster-0.1.2.data/scripts/sort_aster_strips.py
pymmaster-0.1.2.data/scripts/sort_l1a.py
pymmaster-0.1.2.data/scripts/wget_l1a.sh
pymmaster-0.1.2.data/scripts/wrapper_region_sbatch.sh
pymmaster-0.1.2.dist-info/LICENSE
pymmaster-0.1.2.dist-info/METADATA
pymmaster-0.1.2.dist-info/WHEEL
pymmaster-0.1.2.dist-info/top_level.txt
pymmaster-0.1.2.dist-info/RECORD
